gradientcobra/__init__.py
gradientcobra/gradientcobra.py
gradientcobra/mixcobra.py
gradientcobra/superlearner.py
gradientcobra-1.1.6.dist-info/LICENSE
gradientcobra-1.1.6.dist-info/METADATA
gradientcobra-1.1.6.dist-info/WHEEL
gradientcobra-1.1.6.dist-info/top_level.txt
gradientcobra-1.1.6.dist-info/RECORD
