Metadata-Version: 2.2
Name: gradientcobra
Version: 1.1.6
Summary: Python implementation for Gradient COBRA by S. Has (2023) with other aggregation and kernel methods.
Home-page: https://github.com/hassothea/gradientcobra/
Author: Sothea Has
Author-email: sothea.has@lpsm.paris
Keywords: Consensual aggregation,Kernel,Regression,Statistical Aggregation
Classifier: Development Status :: 4 - Beta
Classifier: License :: OSI Approved :: MIT License
Classifier: Programming Language :: Python
Classifier: Operating System :: Microsoft :: Windows
Classifier: Intended Audience :: Science/Research
Classifier: Topic :: Scientific/Engineering
License-File: LICENSE
Requires-Dist: numpy>=1.20.1
Requires-Dist: pandas>=2.1.0
Requires-Dist: scipy>=1.10.1
Requires-Dist: scikit-learn>=1.2
Requires-Dist: matplotlib
Requires-Dist: seaborn
Requires-Dist: kaleido
Requires-Dist: plotly>=5.10.0
Requires-Dist: tqdm
Dynamic: author
Dynamic: author-email
Dynamic: classifier
Dynamic: description
Dynamic: home-page
Dynamic: keywords
Dynamic: requires-dist
Dynamic: summary
